pyterrier_dr/__init__.py
pyterrier_dr/_ils.py
pyterrier_dr/_mmr.py
pyterrier_dr/bge_m3.py
pyterrier_dr/biencoder.py
pyterrier_dr/cde.py
pyterrier_dr/electra.py
pyterrier_dr/hgf_models.py
pyterrier_dr/indexes.py
pyterrier_dr/prf.py
pyterrier_dr/sbert_models.py
pyterrier_dr/tctcolbert_model.py
pyterrier_dr/util.py
pyterrier_dr/flex/__init__.py
pyterrier_dr/flex/core.py
pyterrier_dr/flex/corpus_graph.py
pyterrier_dr/flex/diversity.py
pyterrier_dr/flex/faiss_retr.py
pyterrier_dr/flex/flatnav_retr.py
pyterrier_dr/flex/gar.py
pyterrier_dr/flex/ladr.py
pyterrier_dr/flex/np_retr.py
pyterrier_dr/flex/scann_retr.py
pyterrier_dr/flex/torch_retr.py
pyterrier_dr/flex/voyager_retr.py
pyterrier_dr/pt_docs/diversity.rst
pyterrier_dr/pt_docs/encoding.rst
pyterrier_dr/pt_docs/index.rst
pyterrier_dr/pt_docs/indexing-retrieval.rst
pyterrier_dr/pt_docs/overview.rst
pyterrier_dr/pt_docs/prf.rst
pyterrier_dr-0.6.2.dist-info/licenses/LICENSE
pyterrier_dr-0.6.2.dist-info/METADATA
pyterrier_dr-0.6.2.dist-info/WHEEL
pyterrier_dr-0.6.2.dist-info/entry_points.txt
pyterrier_dr-0.6.2.dist-info/top_level.txt
pyterrier_dr-0.6.2.dist-info/RECORD
