Metadata-Version: 2.4
Name: pyterrier-dr
Version: 0.6.2
Summary: Dense Retrieval for PyTerrier
Author-email: Sean MacAvaney <sean.macavaney@glasgow.ac.uk>
Maintainer-email: Sean MacAvaney <sean.macavaney@glasgow.ac.uk>
Project-URL: Repository, https://github.com/terrierteam/pyterrier_dr
Project-URL: Bug Tracker, https://github.com/terrierteam/pyterrier_dr/issues
Classifier: Programming Language :: Python
Classifier: Operating System :: OS Independent
Classifier: Topic :: Text Processing
Classifier: Topic :: Text Processing :: Indexing
Classifier: License :: OSI Approved :: MIT License
Requires-Python: >=3.8
License-File: LICENSE
Requires-Dist: transformers
Requires-Dist: python-terrier>=0.11.0
Requires-Dist: pyterrier-alpha>=0.10.0
Requires-Dist: torch
Requires-Dist: numpy
Requires-Dist: npids
Requires-Dist: sentence_transformers
Requires-Dist: pyterrier-adaptive
Provides-Extra: bgem3
Requires-Dist: FlagEmbedding; extra == "bgem3"
Dynamic: license-file
